smelt/backend.py
smelt/compiler.py
smelt/frontend.py
smelt/mypycify.py
smelt/nuitkaify.py
smelt/py.typed
smelt/utils.py
smelt/build_backends/hatch.py
smelt/pyconfig/aarch64-linux-gnu/python3.12/pyconfig.h
smelt/pyconfig/arm-linux-gnueabihf/python3.12/pyconfig.h
smelt-0.3.0.dist-info/METADATA
smelt-0.3.0.dist-info/WHEEL
smelt-0.3.0.dist-info/entry_points.txt
smelt-0.3.0.dist-info/top_level.txt
smelt-0.3.0.dist-info/RECORD
